MANIFEST.in
README.md
setup.py
rubber/__init__.py
rubber/client.py
rubber/instanceutils.py
rubber/models.py
rubber/resource.py
rubber/response.py
rubber/testutils.py
rubber.egg-info/PKG-INFO
rubber.egg-info/SOURCES.txt
rubber.egg-info/dependency_links.txt
rubber.egg-info/requires.txt
rubber.egg-info/top_level.txt
tests/__init__.py
tests/alltests.py