Metadata-Version: 1.1
Name: rubber
Version: 0.1.8
Summary: Elasticsearch client with Django support.
Home-page: https://github.com/cantinasoftware/rubber
Author: Stéphane JAIS
Author-email: stephane@cantinasoftware.com
License: UNKNOWN
Platform: UNKNOWN
Classifier: Development Status :: 3 - Alpha
Classifier: Environment :: Web Environment
Classifier: Framework :: Django
Classifier: Intended Audience :: Developers
Classifier: License :: OSI Approved :: BSD License
Classifier: Operating System :: OS Independent
Classifier: Programming Language :: Python
Classifier: Topic :: Utilities
Requires: requests(>=0.9.0)
